kestra_api_client/__init__.py
kestra_api_client/api_client.py
kestra_api_client/api_response.py
kestra_api_client/configuration.py
kestra_api_client/exceptions.py
kestra_api_client/kestra_client.py
kestra_api_client/py.typed
kestra_api_client/rest.py
kestra_api_client/api/__init__.py
kestra_api_client/api/ai_api.py
kestra_api_client/api/apps_api.py
kestra_api_client/api/audit_logs_api.py
kestra_api_client/api/auths_api.py
kestra_api_client/api/banners_api.py
kestra_api_client/api/bindings_api.py
kestra_api_client/api/blueprint_tags_api.py
kestra_api_client/api/blueprints_api.py
kestra_api_client/api/cluster_api.py
kestra_api_client/api/dashboards_api.py
kestra_api_client/api/default_api.py
kestra_api_client/api/executions_api.py
kestra_api_client/api/files_api.py
kestra_api_client/api/flows_api.py
kestra_api_client/api/groups_api.py
kestra_api_client/api/invitations_api.py
kestra_api_client/api/kv_api.py
kestra_api_client/api/logs_api.py
kestra_api_client/api/maintenance_api.py
kestra_api_client/api/metrics_api.py
kestra_api_client/api/misc_api.py
kestra_api_client/api/namespaces_api.py
kestra_api_client/api/plugins_api.py
kestra_api_client/api/roles_api.py
kestra_api_client/api/scim_configuration_api.py
kestra_api_client/api/scim_groups_api.py
kestra_api_client/api/scim_users_api.py
kestra_api_client/api/security_integrations_api.py
kestra_api_client/api/service_account_api.py
kestra_api_client/api/services_api.py
kestra_api_client/api/tenant_access_api.py
kestra_api_client/api/tenants_api.py
kestra_api_client/api/test_suites_api.py
kestra_api_client/api/triggers_api.py
kestra_api_client/api/users_api.py
kestra_api_client/api/worker_groups_api.py
kestra_api_client/models/__init__.py
kestra_api_client/models/abstract_flow.py
kestra_api_client/models/abstract_flow_labels.py
kestra_api_client/models/abstract_graph.py
kestra_api_client/models/abstract_graph_branch_type.py
kestra_api_client/models/abstract_metric_entry_object.py
kestra_api_client-1.0.0.dist-info/METADATA
kestra_api_client-1.0.0.dist-info/WHEEL
kestra_api_client-1.0.0.dist-info/top_level.txt
kestra_api_client-1.0.0.dist-info/RECORD
